bitable/__init__.py
bitable/api.py
bitable/fieldType.py
bitable/operator.py
bitable/table.py
tests/__init__.py
tests/credentials.py
tests/test_table.py
bitable-1.0.1.dist-info/LICENSE
bitable-1.0.1.dist-info/METADATA
bitable-1.0.1.dist-info/WHEEL
bitable-1.0.1.dist-info/top_level.txt
bitable-1.0.1.dist-info/RECORD
