Metadata-Version: 2.2
Name: bitable
Version: 1.0.1
Summary: A Python package to operate with Feishu/Lark bitable
Home-page: https://github.com/bigeyex/python-bitable
Author: Yu Wang (bigeyex)
Author-email: bigeyex@gmail.com
Classifier: Programming Language :: Python :: 3
Classifier: License :: OSI Approved :: MIT License
Classifier: Operating System :: OS Independent
Requires-Python: >=3.6
License-File: LICENSE
Requires-Dist: requests==2.32.3
Dynamic: author
Dynamic: author-email
Dynamic: classifier
Dynamic: description
Dynamic: description-content-type
Dynamic: home-page
Dynamic: requires-dist
Dynamic: requires-python
Dynamic: summary
